kmr/__init__.py
kmr/mod.py
kmr-0.1.dist-info/METADATA
kmr-0.1.dist-info/WHEEL
kmr-0.1.dist-info/top_level.txt
kmr-0.1.dist-info/RECORD
