Metadata-Version: 2.4
Name: kmr
Version: 0.1
Summary: Godot için basit mod aracı
Author: senin_adın
Author-email: email@example.com
Dynamic: author
Dynamic: author-email
Dynamic: summary
